Metadata-Version: 2.1
Name: easywindow
Version: 0.0.1
Summary: A NONDOS Project
Home-page: 
Author: NONDOS
Author-email: easywindow@gmx.com
License: MIT
Keywords: tkinter
Platform: UNKNOWN
Classifier: Development Status :: 5 - Production/Stable
Classifier: Intended Audience :: Education
Classifier: Operating System :: Microsoft :: Windows :: Windows 10
Classifier: License :: OSI Approved :: MIT License
Classifier: Programming Language :: Python :: 3
License-File: LICENCE.txt
